autosktime/__init__.py
autosktime/automl.py
autosktime/constants.py
autosktime/smbo.py
autosktime/automl_common/__init__.py
autosktime/automl_common/setup.py
autosktime/automl_common/common/__init__.py
autosktime/automl_common/common/ensemble_building/__init__.py
autosktime/automl_common/common/ensemble_building/abstract_ensemble.py
autosktime/automl_common/common/utils/__init__.py
autosktime/automl_common/common/utils/backend.py
autosktime/automl_common/common/utils/logging.yaml
autosktime/automl_common/common/utils/logging_.py
autosktime/automl_common/test/test_util/__init__.py
autosktime/automl_common/test/test_util/example_config.yaml
autosktime/automl_common/test/test_util/test_backend.py
autosktime/automl_common/test/test_util/test_logging.py
autosktime/data/__init__.py
autosktime/data/splitter.py
autosktime/data/benchmark/__init__.py
autosktime/data/benchmark/base.py
autosktime/data/benchmark/cmapss.py
autosktime/data/benchmark/femto_bearing.py
autosktime/data/benchmark/filtration.py
autosktime/data/benchmark/m4.py
autosktime/data/benchmark/phm08.py
autosktime/data/benchmark/phme20.py
autosktime/data/benchmark/data/__init__.py
autosktime/data/benchmark/data/CMAPSS/RUL_FD001.txt
autosktime/data/benchmark/data/CMAPSS/RUL_FD002.txt
autosktime/data/benchmark/data/CMAPSS/RUL_FD003.txt
autosktime/data/benchmark/data/CMAPSS/RUL_FD004.txt
autosktime/data/benchmark/data/CMAPSS/__init__.py
autosktime/data/benchmark/data/CMAPSS/test_FD001.txt
autosktime/data/benchmark/data/CMAPSS/test_FD002.txt
autosktime/data/benchmark/data/CMAPSS/test_FD003.txt
autosktime/data/benchmark/data/CMAPSS/test_FD004.txt
autosktime/data/benchmark/data/CMAPSS/train_FD001.txt
autosktime/data/benchmark/data/CMAPSS/train_FD002.txt
autosktime/data/benchmark/data/CMAPSS/train_FD003.txt
autosktime/data/benchmark/data/CMAPSS/train_FD004.txt
autosktime/data/benchmark/data/PHME20DataChallenge/__init__.py
autosktime/data/benchmark/data/PHME20DataChallenge/Training/__init__.py
auto_sktime-0.1.0.dist-info/LICENSE.txt
auto_sktime-0.1.0.dist-info/METADATA
auto_sktime-0.1.0.dist-info/WHEEL
auto_sktime-0.1.0.dist-info/top_level.txt
auto_sktime-0.1.0.dist-info/RECORD
