Metadata-Version: 2.1
Name: auto-sktime
Version: 0.1.0
Summary: Automatic creation of time series forecasts, regression and classification
Home-page: https://github.com/Ennosigaeon/auto-sktime/
Author: Marc Zoeller
Author-email: marc.zoeller@usu.com
License: MIT
Project-URL: Documentation, https://github.com/Ennosigaeon/auto-sktime/
Project-URL: Source, https://github.com/Ennosigaeon/auto-sktime/
Platform: any
Classifier: Development Status :: 4 - Beta
Classifier: Programming Language :: Python
Requires-Python: >=3.8
License-File: LICENSE.txt
Requires-Dist: sktime (==0.13.0)
Requires-Dist: ConfigSpace (~=0.6.0)
Requires-Dist: smac (~=1.4.0)
Requires-Dist: matplotlib (~=3.6.2)
Requires-Dist: seaborn (~=0.12.1)
Requires-Dist: tsmoothie (~=1.0.4)
Requires-Dist: tsfresh (~=0.19.0)
Requires-Dist: torch (~=1.13.0)
Requires-Dist: numpy (~=1.22.0)
Requires-Dist: importlib-metadata ; python_version < "3.8"
Provides-Extra: testing
Requires-Dist: setuptools ; extra == 'testing'
Requires-Dist: pytest ; extra == 'testing'
Requires-Dist: pytest-cov ; extra == 'testing'
